mortie-0.4.6.dist-info/METADATA
mortie-0.4.6.dist-info/WHEEL
mortie-0.4.6.dist-info/licenses/LICENSE
mortie/__init__.py
mortie/_rustie.abi3.so
mortie/tests/Ant_Grounded_DrainageSystem_Polygons.txt
mortie/tests/Ant_Grounded_DrainageSystem_Polygons_morton.npz
mortie/tests/__init__.py
mortie/tests/test_main_api.py
mortie/tests/test_morton_counts.py
mortie/tests/test_polygon_regression.py
mortie/tests/test_tools.py
mortie/tools.py
mortie-0.4.6.dist-info/RECORD
