Metadata-Version: 2.4
Name: mortie
Version: 0.4.6
Classifier: Programming Language :: Python :: 3
Classifier: License :: OSI Approved :: MIT License
Classifier: Operating System :: OS Independent
Requires-Dist: numpy>=1.20
Requires-Dist: healpy
Requires-Dist: pytest>=8.0 ; extra == 'test'
Requires-Dist: pytest-cov>=4.0 ; extra == 'test'
Provides-Extra: test
License-File: LICENSE
Summary: Morton numbering and indexing for healpix grids
Author-email: "Shane Grigsby (espg)" <refuge@rocktalus.com>
Requires-Python: >=3.10
Project-URL: Homepage, https://github.com/espg/mortie
Project-URL: Bug Tracker, https://github.com/espg/mortie/issues
